Metadata-Version: 2.1
Name: plotstandarddeviation
Version: 0.0.3
Summary: Calculates all standard deviations from the mean within a dataset's range.
Home-page: 
Author: Alexander Levon Schulze
Author-email: alexanderlevonschulze@gmail.com
License: MIT
Keywords: standard_deviation,calculator
Classifier: Development Status :: 5 - Production/Stable
Classifier: Intended Audience :: Science/Research
Classifier: Operating System :: Microsoft :: Windows :: Windows 11
Classifier: License :: OSI Approved :: MIT License
Classifier: Programming Language :: Python :: 3
Classifier: Natural Language :: English
License-File: LICENSE.txt
Requires-Dist: numpy
Requires-Dist: pandas
